{
  "pineal_visual_frequencies": {
    "metadata": {
      "total_signatures": 28,
      "discovery_date": "2025-08-31", 
      "research_classification": "PIN00-COMPLETE",
      "primary_mechanism": "crystalline_light_transduction",
      "frequency_range": "1.53-80Hz"
    },
    "octave_cascade_series": {
      "VIS-80-PHOTORECEPTOR": {
        "frequency": 80.0,
        "function": "photoreceptor_transduction",
        "cell_type": "rods_cones",
        "response_time": 0.0125,
        "signal_amplification": 1000000,
        "wavelength_sensitivity": [400, 700],
        "octave_relationship": "4th_octave_above_20Hz"
      },
      "VIS-40-GAMMA-BINDING": {
        "frequency": 40.0,
        "function": "consciousness_binding",
        "cell_type": "visual_cortex_neurons", 
        "binding_range": "entire_visual_field",
        "attention_enhancement": 2.3,
        "memory_encoding_rate": 0.87,
        "octave_relationship": "2nd_octave_above_20Hz"
      },
      "VIS-20-LGN-PROCESSING": {
        "frequency": 20.0,
        "function": "lateral_geniculate_processing",
        "cell_type": "thalamic_relay_neurons",
        "contrast_enhancement": 3.4,
        "binocular_integration": 0.92,
        "motion_detection": "primary",
        "octave_relationship": "1st_octave_above_10Hz"
      },
      "VIS-10-ALPHA-INTEGRATION": {
        "frequency": 10.0,
        "function": "alpha_wave_visual_integration", 
        "cell_type": "occipital_cortex",
        "pattern_recognition": 0.78,
        "spatial_integration": "3D_scene_construction",
        "pineal_coupling": "direct_pathway",
        "octave_relationship": "fundamental_visual_frequency"
      },
      "OCT-CASCADE-80-40": {
        "frequency_ratio": 2.0,
        "relationship": "perfect_octave",
        "coupling_strength": 0.89,
        "phase_stability": 0.94
      },
      "OCT-CASCADE-40-20": {
        "frequency_ratio": 2.0,
        "relationship": "perfect_octave", 
        "coupling_strength": 0.91,
        "phase_stability": 0.96
      },
      "OCT-CASCADE-20-10": {
        "frequency_ratio": 2.0,
        "relationship": "perfect_octave",
        "coupling_strength": 0.88,
        "phase_stability": 0.93
      },
      "GOLDEN-RATIO-DMT-SCHUMANN": {
        "dmt_frequency": 13.5,
        "schumann_frequency": 7.83,
        "ratio": 1.72,
        "golden_ratio_approximation": 1.618,
        "deviation": 0.102,
        "significance": "consciousness_interface_bridge"
      }
    },
    "pineal_crystallization": {
      "CRY-SIL-358": {
        "frequency": 3.58,
        "crystal_type": "silicon_based",
        "anchor": "Sol-Silicon",
        "formation_temperature": 310,
        "structure": "hexagonal_close_packed",
        "piezoelectric_constant": 2.3e-12,
        "light_sensitivity_peak": 500,
        "optimal_thickness": 75e-6
      },
      "CRY-CAL-511": {
        "frequency": 5.11,
        "crystal_type": "calcium_carbonate",
        "anchor": "Sol-Calcium", 
        "formation_mechanism": "age_related_calcification",
        "crystal_polymorphs": ["calcite", "aragonite"],
        "resonance_type": "mechanical_to_electrical",
        "optimal_thickness": 125e-6
      },
      "CRY-PIE-783": {
        "frequency": 7.83,
        "crystal_type": "piezoelectric_response",
        "mechanism": "mechanical_vibration_to_electrical_signal",
        "schumann_coupling": "primary",
        "sensitivity": 4.7e-11,
        "response_time": 0.128
      },
      "CRY-STW-186": {
        "frequency": 1.86,
        "crystal_type": "structured_water_matrix",
        "mechanism": "H-O_beat_frequency_from_primordial",
        "function": "crystal_nucleation_and_growth",
        "organization": "hexagonal_templates",
        "ion_conductivity_enhancement": 2.8,
        "memory_storage": "optical_interference_patterns"
      },
      "CRY-FORMATION-CASCADE": {
        "water_template": 1.86,
        "silicon_deposition": 3.58,
        "calcium_accumulation": 5.11,
        "piezoelectric_activation": 7.83,
        "sequence": "sequential_frequency_dependent"
      },
      "CRY-DECALCIFICATION-PROTOCOL": {
        "structured_water_frequency": 1.86,
        "duration": 900,
        "healthy_silicon_frequency": 3.58,
        "duration_silicon": 600,
        "optimization_note": "dissolves_pathological_calcium"
      }
    },
    "schumann_coupling": {
      "SCH-PRIMARY-783": {
        "frequency": 7.83,
        "source": "earth_schumann_resonance_fundamental",
        "melatonin_entrainment": 0.94,
        "circadian_coupling": "primary_synchronizer",
        "seasonal_variation": 0.5,
        "geographic_sensitivity": "latitude_longitude_dependent"
      },
      "SCH-PPT-TRIANGLE": {
        "frequency": 7.83,
        "organs": ["pineal", "pancreas", "thymus"],
        "immune_coupling": 0.87,
        "metabolic_sync": 0.79,
        "consciousness_coherence": 0.91,
        "healing_acceleration": 2.4
      },
      "SCH-HARMONIC-1566": {
        "frequency": 15.66,
        "harmonic": "2nd",
        "effect": "enhanced_alertness",
        "coupling_strength": 0.67
      },
      "SCH-HARMONIC-2349": {
        "frequency": 23.49,
        "harmonic": "3rd", 
        "effect": "cognitive_acceleration",
        "coupling_strength": 0.45
      }
    },
    "dmt_consciousness_interface": {
      "DMT-PRIMARY-135": {
        "frequency": 13.5,
        "mechanism": "consciousness_interface",
        "brain_region": "pineal_gland",
        "visual_enhancement": 3.0,
        "perception_acuity_increase": 300,
        "frequency_bridge": "7.83_to_20Hz",
        "golden_ratio_factor": 1.72
      },
      "DMT-ALPHA-ENHANCEMENT": {
        "frequency_range": [8, 12],
        "state": "relaxed_visual_awareness",
        "coupling_strength": 0.73
      },
      "DMT-ACTIVATION-THRESHOLD": {
        "frequency_range": [13, 14],
        "state": "activation_threshold",
        "endogenous_production": "pineal_synthesis"
      },
      "DMT-VISIONARY-SUSTAINED": {
        "frequency_range": [14, 16], 
        "state": "sustained_visionary",
        "integration_coupling": 0.82
      },
      "DMT-MOLECULAR-RESONANCE": {
        "tryptophan_precursor": 14.2,
        "serotonin_intermediate": 12.8,
        "dmt_final_product": 13.5,
        "mao_inhibition": 11.7
      }
    },
    "memory_holography": {
      "MEM-MYELIC-27": {
        "frequency": 27.0,
        "mechanism": "myelic_fluid_holography",
        "storage_type": "optical_interference_patterns",
        "capacity": "unlimited_holographic",
        "retrieval_speed": 0.037,
        "consciousness_integration": 0.89
      },
      "MEM-VISUAL-ENCODING": {
        "frequency": 27.0,
        "visual_scene_storage": "complete_3D_hologram",
        "color_depth": 16777216,
        "spatial_resolution": "submicrometer",
        "temporal_resolution": 0.001
      },
      "MEM-PATTERN-ACCESS": {
        "frequency": 27.0,
        "access_time": 0.001,
        "parallel_retrieval": "unlimited",
        "cross_reference": "instantaneous",
        "degradation_rate": 0.0
      }
    },
    "therapeutic_protocols": {
      "DECALCIFICATION-FULL": {
        "frequencies": [1.86, 3.58, 7.83, 13.5],
        "durations": [900, 600, 1200, 300],
        "sequence": "sequential",
        "total_duration": 3000,
        "effectiveness": 0.87
      },
      "VISUAL-ENHANCEMENT-DAILY": {
        "morning_40Hz": 300,
        "midday_20Hz": 600, 
        "evening_783Hz": 900,
        "night_135Hz": 180,
        "total_daily": 1980,
        "enhancement_factor": 2.1
      },
      "CONSCIOUSNESS-ACTIVATION": {
        "primary_frequency": 13.5,
        "duration": 300,
        "preparation_783Hz": 600,
        "integration_27Hz": 180,
        "safety_rating": "mild_enhancement"
      },
      "CIRCADIAN-RESET": {
        "schumann_783Hz": 1800,
        "timing": "sunset_plus_2hours",
        "effectiveness": 0.93,
        "sleep_quality_improvement": 2.4
      }
    },
    "stellar_anchor_connections": {
      "SOL-ANCHOR-VISUAL": {
        "carbon": 1.53,
        "oxygen": 2.04, 
        "silicon": 3.58,
        "calcium": 5.11,
        "total_elements": 4,
        "frequency_range": [1.53, 5.11],
        "harmonic_relationships": "golden_ratio_connected",
        "stability_factor": "consistent_stellar_resonance"
      },
      "VISUAL-SYSTEM-COMPLETENESS": {
        "sol_anchor_coverage": 1.0,
        "primary_elements": ["C", "O", "Si", "Ca"],
        "functions": ["structure", "transport", "crystals", "signaling"],
        "frequency_precision": 0.02,
        "evolutionary_stability": "maximum"
      }
    },
    "primordial_connections": {
      "STRUCTURED-WATER-CONTINUITY": {
        "primordial_frequency": 1.86,
        "pineal_frequency": 1.86,
        "mechanism": "H-O_beat_frequency",
        "evolutionary_significance": "consciousness_from_primordial_cymatics",
        "continuity": "perfect_match"
      },
      "UNIVERSAL-RESONANCE-PRINCIPLE": {
        "primordial_soup": 1.86,
        "pineal_evolution": 1.86, 
        "visual_consciousness": "harmonic_cascade_from_primordial",
        "modern_biology": "preserves_original_relationships",
        "conclusion": "pineal_is_living_fossil_of_cymatic_organization"
      }
    }
  }
}